{ //Song ID based on wikipedia: https://en.wikipedia.org/wiki/List_of_Pump_It_Up_songs
  "Version": "1.4",
  "Musics": [
    // -- Special characters --
    {
      "SongBanner": "https://pumpout2.anyhowstep.com:17593/img/card/xx-percent-x.png",
      "SongTitle": "%X",
      "SongId": "1620",
      "SongArtist": "Pory",
      "Charts": [
        {
          "Done": "False",
          "Level": "D19",
          "Require": [
            {
              "Done": "False",
              "Description": "At least D13 SS"
            }
          ]
        }
      ]
    },
    // -- 0~9 --
    {
      "SongBanner": "https://pumpout2.anyhowstep.com:17593/img/card/xx-1949.png",
      "SongTitle": "1949",
      "SongId": "1605",
      "SongArtist": "SLAM",
      "Charts": [
        {
          "Done": "False",
          "Level": "S21",
          "Require": [
            {
              "Done": "False",
              "Description": "At least S16 A"
            },
            {
              "Done": "False",
              "Description": "1950 S20 PASS (with at least A)"
            }
          ]
        },
        {
          "Done": "False",
          "Level": "S23",
          "Require": [
            {
              "Done": "False",
              "Description": "Random, or Play it with someone who has this"
            },
            {
              "Done": "False",
              "Description": "1950 S23 PASS (with at least A)"
            }
          ]
        },
        {
          "Done": "False",
          "Level": "D26",
          "Require": [
            {
              "Done": "False",
              "Description": "Clear 50 mission zone quests, or Clear Ignis Fatuus D27 mission"
            }
          ]
        }
      ]
    },
    {
      "SongBanner": "https://pumpout2.anyhowstep.com:17593/img/card/xx-86.png",
      "SongTitle": "86",
      "SongId": "1670",
      "SongArtist": "DASU",
      "Charts": [
        {
          "Done": "False",
          "Level": "S-X",
          "Require": [
            {
              "Done": "False",
              "Description": "All Charts: Acquire SSS 86 times"
            }
          ]
        }
      ]
    },
    {
      "SongBanner": "https://pumpout2.anyhowstep.com:17593/img/card/xx-86-full-song.png",
      "SongTitle": "86 (Full Song)",
      "SongId": "16F7",
      "SongArtist": "DASU",
      "Charts": [
        {
          "Done": "False",
          "Level": "S16",
          "Require": [
            {
              "Done": "False",
              "Description": "Nakakapagpabagabab PASS (with at least A)"
            },
            {
              "Done": "False",
              "Description": "86 stage PASS (with at least A)"
            }
          ]
        },
        {
          "Done": "False",
          "Level": "S21",
          "Require": [
            {
              "Done": "False",
              "Description": "Nakakapagpabagabab PASS (with at least A)"
            },
            {
              "Done": "False",
              "Description": "86 stage PASS (with at least A)"
            }
          ]
        },
        {
          "Done": "False",
          "Level": "D23",
          "Require": [
            {
              "Done": "False",
              "Description": "Nakakapagpabagabab PASS (with at least A)"
            },
            {
              "Done": "False",
              "Description": "86 stage PASS (with at least A)"
            }
          ]
        }
      ]
    },
    // -- A --
    {
      "SongBanner": "https://pumpout2.anyhowstep.com:17593/img/card/xx-allegro-con-fuoco-full.png",
      "SongTitle": "Allegro Con Fuoco (Full Song)",
      "SongId": "16C5",
      "SongArtist": "DM Ashura",
      "Charts": [
        {
          "Done": "False",
          "Level": "S23",
          "Require": [
            {
              "Done": "False",
              "Description": "Allegro Piu Mosso S19 PASS (with at least A)"
            },
            {
              "Done": "False",
              "Description": "Allegro con Fuoco S22 PASS (with at least A)"
            },
            {
              "Done": "False",
              "Description": "Allegro Furioso S20 PASS (with at least A)"
            }
          ]
        },
        {
          "Done": "False",
          "Level": "D25",
          "Require": [
            {
              "Done": "False",
              "Description": "Allegro Piu Mosso D19 PASS (with at least A)"
            },
            {
              "Done": "False",
              "Description": "Allegro con Fuoco D23 PASS (with at least A)"
            },
            {
              "Done": "False",
              "Description": "Allegro Furioso D20 PASS (with at least A)"
            }
          ]
        }
      ]
    },
    // -- B --
    {
      "SongBanner": "https://pumpout2.anyhowstep.com:17593/img/card/xx-bboom-bboom.png",
      "SongTitle": "BBoom BBoom",
      "SongId": "16E0",
      "SongArtist": "Momoland",
      "Charts": [
        {
          "Done": "False",
          "Level": "S15",
          "Require": [
            {
              "Done": "False",
              "Description": "At least S13 A"
            }
          ]
        },
        {
          "Done": "False",
          "Level": "D18",
          "Require": [
            {
              "Done": "False",
              "Description": "At least S on S15 & D15"
            }
          ]
        }
      ]
    },
    {
      "SongBanner": "https://pumpout2.anyhowstep.com:17593/img/card/1646.png",
      "SongTitle": "Black Cat",
      "SongId": "1646",
      "SongArtist": "Turbo",
      "Charts": [
        {
          "Done": "False",
          "Level": "S17",
          "Require": [
            {
              "Done": "False",
              "Description": "At least S14 A"
            }
          ]
        },
        {
          "Done": "False",
          "Level": "D18",
          "Require": [
            {
              "Done": "False",
              "Description": "At least D16 A"
            }
          ]
        }
      ]
    },
    {
      "SongBanner": "https://pumpout2.anyhowstep.com:17593/img/card/xx-black-swan.png",
      "SongTitle": "Black Swan",
      "SongId": "1679",
      "SongArtist": "Zeron",
      "Charts": [
        {
          "Done": "False",
          "Level": "S12",
          "Require": [
            {
              "Done": "False",
              "Description": "AM.Pass level 10"
            }
          ]
        },
        {
          "Done": "False",
          "Level": "S14",
          "Require": [
            {
              "Done": "False",
              "Description": "AM.Pass level 12"
            }
          ]
        },
        {
          "Done": "False",
          "Level": "S19",
          "Require": [
            {
              "Done": "False",
              "Description": "AM.Pass level 16"
            }
          ]
        },
        {
          "Done": "False",
          "Level": "D15",
          "Require": [
            {
              "Done": "False",
              "Description": "AM.Pass level 18"
            }
          ]
        },
        {
          "Done": "False",
          "Level": "D22",
          "Require": [
            {
              "Done": "False",
              "Description": "At least D15 SS"
            }
          ]
        }
      ]
    },
    {
      "SongBanner": "https://pumpout2.anyhowstep.com:17593/img/card/xx-boomerang.png",
      "SongTitle": "Boomerang",
      "SongId": "1651",
      "SongArtist": "Wanna One",
      "Charts": [
        {
          "Done": "False",
          "Level": "S14",
          "Require": [
            {
              "Done": "False",
              "Description": "AM.Pass Login"
            }
          ]
        },
        {
          "Done": "False",
          "Level": "S17",
          "Require": [
            {
              "Done": "False",
              "Description": "At least S14 A"
            }
          ]
        },
        {
          "Done": "False",
          "Level": "D16",
          "Require": [
            {
              "Done": "False",
              "Description": "D7 SSS"
            }
          ]
        },
        {
          "Done": "False",
          "Level": "D20",
          "Require": [
            {
              "Done": "False",
              "Description": "At least S on S17 & D16"
            }
          ]
        },
        {
          "Done": "False",
          "Level": "CO-OP X 2",
          "Require": [
            {
              "Done": "False",
              "Description": "Play (and pass) co-op charts ~50 times (idk the number yet)"
            }
          ]
        }
      ]
    },
    {
      "SongBanner": "https://pumpout2.anyhowstep.com:17593/img/card/xx-boong-boong.png",
      "SongTitle": "Boong Boong (Feat. Sik-K)",
      "SongId": "1667",
      "SongArtist": "HAON, PULLIK",
      "Charts": [
        {
          "Done": "False",
          "Level": "S16",
          "Require": [
            {
              "Done": "False",
              "Description": "At least A on The Little Prince S16"
            }
          ]
        },
        {
          "Done": "False",
          "Level": "D12",
          "Require": [
            {
              "Done": "False",
              "Description": "At least A on The Little Prince D11"
            }
          ]
        },
        {
          "Done": "False",
          "Level": "D19",
          "Require": [
            {
              "Done": "False",
              "Description": "At least A on The Little Prince D19"
            }
          ]
        }
      ]
    },
    // -- C --
    {
      "SongBanner": "https://pumpout2.anyhowstep.com:17593/img/card/913-revive.png",
      "SongTitle": "Can Can",
      "SongId": "913",
      "SongArtist": "Radetzky",
      "Charts": [
        {
          "Done": "False",
          "Level": "S20",
          "Require": [
            {
              "Done": "False",
              "Description": "Advanced Lv. 2 Title"
            }
          ]
        },
        {
          "Done": "False",
          "Level": "D22",
          "Require": [
            {
              "Done": "False",
              "Description": "AM.Pass level 40"
            }
          ]
        }
      ]
    },
    {
      "SongBanner": "https://pumpout2.anyhowstep.com:17593/img/card/16A0.png",
      "SongTitle": "Can Can ~Orpheus in The Party Mix~",
      "SongId": "16A0",
      "SongArtist": "Sr. Lan Belmont",
      "Charts": [
        {
          "Done": "False",
          "Level": "S22",
          "Require": [
            {
              "Done": "False",
              "Description": "At least S on Radetzky Can Can S16"
            }
          ]
        },
        {
          "Done": "False",
          "Level": "D23",
          "Require": [
            {
              "Done": "False",
              "Description": "At least S on Radetzky Can Can D17"
            }
          ]
        }
      ]
    },
    {
      "SongBanner": "https://pumpout2.anyhowstep.com:17593/img/card/16F2.png",
      "SongTitle": "Can-can ~Orpheus in The Party Mix~ (Shortcut)",
      "SongId": "16F2",
      "SongArtist": "Sr. Lan Belmont",
      "Charts": [
        {
          "Done": "False",
          "Level": "D15",
          "Require": [
            {
              "Done": "False",
              "Description": "Get >800k points on D13"
            }
          ]
        },
        {
          "Done": "False",
          "Level": "D17",
          "Require": [
            {
              "Done": "False",
              "Description": "Get >800k points on D15"
            }
          ]
        },
        {
          "Done": "False",
          "Level": "D19",
          "Require": [
            {
              "Done": "False",
              "Description": "Get >800k points on D17"
            }
          ]
        },
        {
          "Done": "False",
          "Level": "D21",
          "Require": [
            {
              "Done": "False",
              "Description": "Get >800k points on D19"
            }
          ]
        },
        {
          "Done": "False",
          "Level": "D23",
          "Require": [
            {
              "Done": "False",
              "Description": "Get >1.8 million points on D21"
            }
          ]
        },
        {
          "Done": "False",
          "Level": "D25",
          "Require": [
            {
              "Done": "False",
              "Description": "Get >1.8 million points on D23"
            }
          ]
        }
      ]
    },
    {
      "SongBanner": "https://pumpout2.anyhowstep.com:17593/img/card/1623.png",
      "SongTitle": "Carmen Bus",
      "SongId": "1623",
      "SongArtist": "StaticSphere & FUGU SUISAN",
      "Charts": [
        {
          "Done": "False",
          "Level": "S18",
          "Require": [
            {
              "Done": "False",
              "Description": "At least S16 A"
            }
          ]
        },
        {
          "Done": "False",
          "Level": "S21",
          "Require": [
            {
              "Done": "False",
              "Description": "At least S18 S"
            }
          ]
        },
        {
          "Done": "False",
          "Level": "D20",
          "Require": [
            {
              "Done": "False",
              "Description": "At least D13 SS"
            }
          ]
        },
        {
          "Done": "False",
          "Level": "D22",
          "Require": [
            {
              "Done": "False",
              "Description": "At least D20 A"
            }
          ]
        }
      ]
    },
    {
      "SongBanner": "https://pumpout2.anyhowstep.com:17593/img/card/xx-club-night.png",
      "SongTitle": "Club Night",
      "SongId": "1668",
      "SongArtist": "Matduke",
      "Charts": [
        {
          "Done": "False",
          "Level": "S18",
          "Require": [
            {
              "Done": "False",
              "Description": "At least S16 A"
            }
          ]
        },
        {
          "Done": "False",
          "Level": "S22",
          "Require": [
            {
              "Done": "False",
              "Description": "At least S18 S"
            }
          ]
        },
        {
          "Done": "False",
          "Level": "D12",
          "Require": [
            {
              "Done": "False",
              "Description": "At least D12 A on Loki"
            }
          ]
        },
        {
          "Done": "False",
          "Level": "D18",
          "Require": [
            {
              "Done": "False",
              "Description": "At least D12 SS"
            }
          ]
        },
        {
          "Done": "False",
          "Level": "D21",
          "Require": [
            {
              "Done": "False",
              "Description": "Advanced Lv. 3 Title"
            }
          ]
        },
        {
          "Done": "False",
          "Level": "CO-OP",
          "Require": [
            {
              "Done": "False",
              "Description": "[CO-OP] Intermediate Title"
            }
          ]
        }
      ]
    },
    {
      "SongBanner": "https://pumpout2.anyhowstep.com:17593/img/card/1676.png",
      "SongTitle": "Conflict",
      "SongId": "1676",
      "SongArtist": "siromaru, Cranky",
      "Charts": [
        {
          "Done": "False",
          "Level": "S22",
          "Require": [
            {
              "Done": "False",
              "Description": "At least S19 SS"
            }
          ]
        },
        {
          "Done": "False",
          "Level": "D24",
          "Require": [
            {
              "Done": "False",
              "Description": "At least D21 S"
            }
          ]
        }
      ]
    },
    {
      "SongBanner": "https://pumpout2.anyhowstep.com:17593/img/card/1671.png",
      "SongTitle": "CROSS SOUL",
      "SongId": "1671",
      "SongArtist": "HyuN feat. Syepias",
      "Charts": [
        {
          "Done": "False",
          "Level": "S20",
          "Require": [
            {
              "Done": "False",
              "Description": "At least S17 A"
            },
            {
              "Done": "False",
              "Description": "At least Cross Over S18 A"
            }
          ]
        },
        {
          "Done": "False",
          "Level": "S22",
          "Require": [
            {
              "Done": "False",
              "Description": "At least S20 A"
            },
            {
              "Done": "False",
              "Description": "At least Cross Over S22 A"
            }
          ]
        },
        {
          "Done": "False",
          "Level": "D20",
          "Require": [
            {
              "Done": "False",
              "Description": "At least D18 A"
            },
            {
              "Done": "False",
              "Description": "At least Cross Over D19 A"
            }
          ]
        },
        {
          "Done": "False",
          "Level": "D24",
          "Require": [
            {
              "Done": "False",
              "Description": "At least D20 A"
            },
            {
              "Done": "False",
              "Description": "At least Cross Over D23 A}"
            }
          ]
        }
      ]
    },
    // -- D --
    {
      "SongBanner": "https://pumpout2.anyhowstep.com:17593/img/card/xx-dement.png",
      "SongTitle": "Dement ~After Legend~",
      "SongId": "1691",
      "SongArtist": "Lunatic Sounds",
      "Charts": [
        {
          "Done": "False",
          "Level": "S23",
          "Require": [
            {
              "Done": "False",
              "Description": "Advanced Lv. 10 Title"
            }
          ]
        },
        {
          "Done": "False",
          "Level": "D26",
          "Require": [
            {
              "Done": "False",
              "Description": "Expert Lv. 3 Title"
            }
          ]
        }
      ]
    },
    {
      "SongBanner": "https://pumpout2.anyhowstep.com:17593/img/card/xx-desaparecer.png",
      "SongTitle": "Desaparecer",
      "SongId": "16D0",
      "SongArtist": "Applesoda vs Max",
      "Charts": [
        {
          "Done": "False",
          "Level": "S20",
          "Require": [
            {
              "Done": "False",
              "Description": "AM.Pass level 100"
            }
          ]
        },
        {
          "Done": "False",
          "Level": "S22",
          "Require": [
            {
              "Done": "False",
              "Description": "AM.Pass level 100"
            }
          ]
        },
        {
          "Done": "False",
          "Level": "D23",
          "Require": [
            {
              "Done": "False",
              "Description": "AM.Pass level 100"
            }
          ]
        }
      ]
    },
    {
      "SongBanner": "https://pumpout2.anyhowstep.com:17593/img/card/A08-xx.png",
      "SongTitle": "Dignity",
      "SongId": "A08",
      "SongArtist": "Crash",
      "Charts": [
        {
          "Done": "False",
          "Level": "D26",
          "Require": [
            {
              "Done": "False",
              "Description": "At least D24 S"
            }
          ]
        }
      ]
    },
    // -- E --
    // -- F --
    {
      "SongBanner": "https://pumpout2.anyhowstep.com:17593/img/card/1675.png",
      "SongTitle": "F(R)IEND",
      "SongId": "1675",
      "SongArtist": "D_AAN",
      "Charts": [
        {
          "Done": "False",
          "Level": "S21",
          "Require": [
            {
              "Done": "False",
              "Description": "At least S on S10"
            },
            {
              "Done": "False",
              "Description": "At least S on S15"
            },
            {
              "Done": "False",
              "Description": "At least S on S19"
            }
          ]
        },
        {
          "Done": "False",
          "Level": "S24",
          "Require": [
            {
              "Done": "False",
              "Description": "At least A on S21"
            }
          ]
        },
        {
          "Done": "False",
          "Level": "D21",
          "Require": [
            {
              "Done": "False",
              "Description": "At least S on D12"
            },
            {
              "Done": "False",
              "Description": "At least S D17"
            }
          ]
        },
        {
          "Done": "False",
          "Level": "D25",
          "Require": [
            {
              "Done": "False",
              "Description": "At least S on D21"
            }
          ]
        }
      ]
    },
    {
      "SongBanner": "https://pumpout2.anyhowstep.com:17593/img/card/16A2.png",
      "SongTitle": "Fires of Destiny",
      "SongId": "16A2",
      "SongArtist": "Jehezukiel",
      "Charts": [
        {
          "Done": "False",
          "Level": "S20",
          "Require": [
            {
              "Done": "False",
              "Description": "At least S16 S"
            },
            {
              "Done": "False",
              "Description": "At least A on S18"
            }
          ]
        },
        {
          "Done": "False",
          "Level": "D22",
          "Require": [
            {
              "Done": "False",
              "Description": "At least D11 SSS"
            },
            {
              "Done": "False",
              "Description": "At least A onD18"
            }
          ]
        }
      ]
    },
    {
      "SongBanner": "https://pumpout2.anyhowstep.com:17593/img/card/xx-fly-high.png",
      "SongTitle": "Fly High",
      "SongId": "1645",
      "SongArtist": "Dreamcatcher",
      "Charts": [
        {
          "Done": "False",
          "Level": "S18",
          "Require": [
            {
              "Done": "False",
              "Description": "At least A on S15"
            }
          ]
        },
        {
          "Done": "False",
          "Level": "D19",
          "Require": [
            {
              "Done": "False",
              "Description": "At least A on D16"
            }
          ]
        }
      ]
    },
    {
      "SongBanner": "https://pumpout2.anyhowstep.com:17593/img/card/16A4.png",
      "SongTitle": "Forgotten Vampire",
      "SongId": "16A4",
      "SongArtist": "WyvernP",
      "Charts": [
        {
          "Done": "False",
          "Level": "S18",
          "Require": [
            {
              "Done": "False",
              "Description": "At least S on S13"
            },
            {
              "Done": "False",
              "Description": "Atleast A on S16"
            }
          ]
        },
        {
          "Done": "False",
          "Level": "D20",
          "Require": [
            {
              "Done": "False",
              "Description": "At least S on D14"
            },
            {
              "Done": "False",
              "Description": "Atleast A on D17"
            }
          ]
        }
      ]
    },
    {
      "SongBanner": "https://pumpout2.anyhowstep.com:17593/img/card/1643.png",
      "SongTitle": "Full Moon",
      "SongId": "1643",
      "SongArtist": "Dreamcatcher",
      "Charts": [
        {
          "Done": "False",
          "Level": "S20",
          "Require": [
            {
              "Done": "False",
              "Description": "At least S16 S"
            }
          ]
        },
        {
          "Done": "False",
          "Level": "S22",
          "Require": [
            {
              "Done": "False",
              "Description": "At least S20 A"
            }
          ]
        },
        {
          "Done": "False",
          "Level": "D24",
          "Require": [
            {
              "Done": "False",
              "Description": "At least D20 S"
            }
          ]
        }
      ]
    },
    // -- G --
    {
      "SongBanner": "https://pumpout2.anyhowstep.com:17593/img/card/xx-gashina.png",
      "SongTitle": "Gashina",
      "SongId": "1652",
      "SongArtist": "SUNMI",
      "Charts": [
        {
          "Done": "False",
          "Level": "S18",
          "Require": [
            {
              "Done": "False",
              "Description": "At least S14 S"
            }
          ]
        },
        {
          "Done": "False",
          "Level": "D19",
          "Require": [
            {
              "Done": "False",
              "Description": "S18 PASS (with at least A)"
            },
            {
              "Done": "False",
              "Description": "D15 PASS (with at least A)"
            }
          ]
        }
      ]
    },
    {
      "SongBanner": "https://pumpout2.anyhowstep.com:17593/img/card/xx-good-bye.png",
      "SongTitle": "Good Bye",
      "SongId": "1663",
      "SongArtist": "Hong Jin Young",
      "Charts": [
        {
          "Done": "False",
          "Level": "S10",
          "Require": [
            {
              "Done": "False",
              "Description": "At least S10 A on Boomerang"
            }
          ]
        },
        {
          "Done": "False",
          "Level": "S14",
          "Require": [
            {
              "Done": "False",
              "Description": "AM.Pass Login"
            }
          ]
        },
        {
          "Done": "False",
          "Level": "S17",
          "Require": [
            {
              "Done": "False",
              "Description": "At least S14 S"
            }
          ]
        },
        {
          "Done": "False",
          "Level": "D16",
          "Require": [
            {
              "Done": "False",
              "Description": "At least D10 SS"
            }
          ]
        },
        {
          "Done": "False",
          "Level": "D18",
          "Require": [
            {
              "Done": "False",
              "Description": "At least S17 A"
            }
          ]
        },
        {
          "Done": "False",
          "Level": "D21",
          "Require": [
            {
              "Done": "False",
              "Description": "Clear 48 mission zone quests"
            }
          ]
        }
      ]
    },
    // -- H --
    {
      "SongBanner": "https://pumpout2.anyhowstep.com:17593/img/card/xx-hann.png",
      "SongTitle": "Hann (Alone)",
      "SongId": "1647",
      "SongArtist": "(G)I-Dle",
      "Charts": [
        {
          "Done": "False",
          "Level": "S16",
          "Require": [
            {
              "Done": "False",
              "Description": "AM.Pass Login"
            }
          ]
        }
      ]
    },
    {
      "SongBanner": "https://pumpout2.anyhowstep.com:17593/img/card/1616.png",
      "SongTitle": "HEART RABBIT COASTER",
      "SongId": "1616",
      "SongArtist": "nato",
      "Charts": [
        {
          "Done": "False",
          "Level": "S21",
          "Require": [
            {
              "Done": "False",
              "Description": "At least A on S11"
            },
            {
              "Done": "False",
              "Description": "At Least A on S14"
            },
            {
              "Done": "False",
              "Description": "At Least A on S17"
            }
          ]
        },
        {
          "Done": "False",
          "Level": "S23",
          "Require": [
            {
              "Done": "False",
              "Description": "At least S on S17"
            },
            {
              "Done": "False",
              "Description": "At least S on S21"
            }
          ]
        },
        {
          "Done": "False",
          "Level": "D22",
          "Require": [
            {
              "Done": "False",
              "Description": "At least S on D13"
            },
            {
              "Done": "False",
              "Description": "At Least S on D18"
            }
          ]
        },
        {
          "Done": "False",
          "Level": "D25",
          "Require": [
            {
              "Done": "False",
              "Description": "At least A on D22"
            }
          ]
        }
      ]
    },
    {
      "SongBanner": "https://pumpout2.anyhowstep.com:17593/img/card/332.png",
      "SongTitle": "Higgledy Piggledy",
      "SongId": "E24",
      "SongArtist": "BanYa",
      "Charts": [
        {
          "Done": "False",
          "Level": "D20",
          "Require": [
            {
              "Done": "False",
              "Description": "Clear 32 mission zone quests"
            }
          ]
        }
      ]
    },
    // -- I --
    {
      "SongBanner": "https://pumpout2.anyhowstep.com:17593/img/card/xx-i-want-u.png",
      "SongTitle": "I Want U",
      "SongId": "1608",
      "SongArtist": "Max",
      "Charts": [
        {
          "Done": "False",
          "Level": "S19",
          "Require": [
            {
              "Done": "False",
              "Description": "At least S16 A"
            }
          ]
        },
        {
          "Done": "False",
          "Level": "D17",
          "Require": [
            {
              "Done": "False",
              "Description": "At least D13 S"
            }
          ]
        },
        {
          "Done": "False",
          "Level": "D21",
          "Require": [
            {
              "Done": "False",
              "Description": "Advanced Lv. 4 Title"
            }
          ]
        }
      ]
    },
    {
      "SongBanner": "https://pumpout2.anyhowstep.com:17593/img/card/xx-im-so-sick.png",
      "SongTitle": "I'm so Sick",
      "SongId": "1650",
      "SongArtist": "A-Pink",
      "Charts": [
        {
          "Done": "False",
          "Level": "S17",
          "Require": [
            {
              "Done": "False",
              "Description": "At least S15 A"
            }
          ]
        },
        {
          "Done": "False",
          "Level": "D18",
          "Require": [
            {
              "Done": "False",
              "Description": "At least D16 A"
            }
          ]
        },
        {
          "Done": "False",
          "Level": "D20",
          "Require": [
            {
              "Done": "False",
              "Description": "At least S on S15"
            },
            {
              "Done": "False",
              "Description": "At least S on S17"
            },
            {
              "Done": "False",
              "Description": "At least S on D16"
            },
            {
              "Done": "False",
              "Description": "At least S on D18"
            }
          ]
        }
      ]
    },
    {
      "SongBanner": "https://pumpout2.anyhowstep.com:17593/img/card/xx-ice-of-death.png",
      "SongTitle": "Ice of Death",
      "SongId": "1625",
      "SongArtist": "Fiverwater",
      "Charts": [
        {
          "Done": "False",
          "Level": "S20",
          "Require": [
            {
              "Done": "False",
              "Description": "At least S17 S"
            }
          ]
        },
        {
          "Done": "False",
          "Level": "D21",
          "Require": [
            {
              "Done": "False",
              "Description": "At least D17 S"
            }
          ]
        }
      ]
    },
    {
      "SongBanner": "https://pumpout2.anyhowstep.com:17593/img/card/xx-imagination.png",
      "SongTitle": "Imagination",
      "SongId": "1678",
      "SongArtist": "SHK",
      "Charts": [
        {
          "Done": "False",
          "Level": "S12",
          "Require": [
            {
              "Done": "False",
              "Description": "AM.Pass level 20"
            }
          ]
        },
        {
          "Done": "False",
          "Level": "S15",
          "Require": [
            {
              "Done": "False",
              "Description": "AM.Pass level 22"
            }
          ]
        },
        {
          "Done": "False",
          "Level": "S19",
          "Require": [
            {
              "Done": "False",
              "Description": "AM.Pass level 24"
            }
          ]
        },
        {
          "Done": "False",
          "Level": "D16",
          "Require": [
            {
              "Done": "False",
              "Description": "AM.Pass level 26"
            }
          ]
        },
        {
          "Done": "False",
          "Level": "D21",
          "Require": [
            {
              "Done": "False",
              "Description": "AM.Pass level 28"
            }
          ]
        }
      ]
    },
    // -- J --
    {
      "SongBanner": "https://pumpout2.anyhowstep.com:17593/img/card/C07-revive.png",
      "SongTitle": "Jump",
      "SongId": "C07",
      "SongArtist": "BanYa",
      "Charts": [
        {
          "Done": "False",
          "Level": "D18",
          "Require": [
            {
              "Done": "False",
              "Description": "Clear 16 mission zone quests"
            }
          ]
        }
      ]
    },
    // -- K --
    {
      "SongBanner": "https://pumpout2.anyhowstep.com:17593/img/card/xx-kimchi-fingers.png",
      "SongTitle": "Kimchi Fingers",
      "SongId": "1630",
      "SongArtist": "Garlic Squad",
      "Charts": [
        {
          "Done": "False",
          "Level": "S14",
          "Require": [
            {
              "Done": "False",
              "Description": "AM.Pass level 30"
            }
          ]
        },
        {
          "Done": "False",
          "Level": "S17",
          "Require": [
            {
              "Done": "False",
              "Description": "AM.Pass level 32"
            }
          ]
        },
        {
          "Done": "False",
          "Level": "S20",
          "Require": [
            {
              "Done": "False",
              "Description": "AM.Pass level 34"
            }
          ]
        },
        {
          "Done": "False",
          "Level": "D16",
          "Require": [
            {
              "Done": "False",
              "Description": "AM.Pass level 36"
            }
          ]
        },
        {
          "Done": "False",
          "Level": "D21",
          "Require": [
            {
              "Done": "False",
              "Description": "AM.Pass level 38"
            }
          ]
        }
      ]
    },
    {
      "SongBanner": "https://pumpout2.anyhowstep.com:17593/img/card/1665.png",
      "SongTitle": "King of Sales",
      "SongId": "1665",
      "SongArtist": "Norazo",
      "Charts": [
        {
          "Done": "False",
          "Level": "S21",
          "Require": [
            {
              "Done": "False",
              "Description": "At least S18 S"
            }
          ]
        },
        {
          "Done": "False",
          "Level": "D23",
          "Require": [
            {
              "Done": "False",
              "Description": "At least D19 S"
            }
          ]
        }
      ]
    },
    // -- L --
    {
      "SongBanner": "https://pumpout2.anyhowstep.com:17593/img/card/xx-le-grand-rouge.png",
      "SongTitle": "Le Grand Rouge",
      "SongId": "1622",
      "SongArtist": "Kien",
      "Charts": [
        {
          "Done": "False",
          "Level": "S20",
          "Require": [
            {
              "Done": "False",
              "Description": "At least S17 A"
            }
          ]
        },
        {
          "Done": "False",
          "Level": "D22",
          "Require": [
            {
              "Done": "False",
              "Description": "At least D19 A"
            }
          ]
        }
      ]
    },
    {
      "SongBanner": "https://pumpout2.anyhowstep.com:17593/img/card/xx-loki.png",
      "SongTitle": "Loki",
      "SongId": "1690",
      "SongArtist": "Lotze",
      "Charts": [
        {
          "Done": "False",
          "Level": "S12",
          "Require": [
            {
              "Done": "False",
              "Description": "AM.Pass level 40"
            }
          ]
        },
        {
          "Done": "False",
          "Level": "S16",
          "Require": [
            {
              "Done": "False",
              "Description": "AM.Pass level 42"
            }
          ]
        },
        {
          "Done": "False",
          "Level": "S19",
          "Require": [
            {
              "Done": "False",
              "Description": "AM.Pass level 44"
            }
          ]
        },
        {
          "Done": "False",
          "Level": "S21",
          "Require": [
            {
              "Done": "False",
              "Description": "Clear 8 mission zone quests"
            }
          ]
        },
        {
          "Done": "False",
          "Level": "D12",
          "Require": [
            {
              "Done": "False",
              "Description": "AM.Pass level 46"
            }
          ]
        },
        {
          "Done": "False",
          "Level": "D19",
          "Require": [
            {
              "Done": "False",
              "Description": "AM.Pass level 48"
            }
          ]
        }
      ]
    },
    {
      "SongBanner": "https://pumpout2.anyhowstep.com:17593/img/card/xx-love-scenario.png",
      "SongTitle": "Love Scenario",
      "SongId": "1659",
      "SongArtist": "iKON",
      "Charts": [
        {
          "Done": "False",
          "Level": "D14",
          "Require": [
            {
              "Done": "False",
              "Description": "At least S14 A"
            }
          ]
        },
        {
          "Done": "False",
          "Level": "S17",
          "Require": [
            {
              "Done": "False",
              "Description": "At least S14 S"
            }
          ]
        }
      ]
    },
    // -- M --
    {
      "SongBanner": "https://pumpout2.anyhowstep.com:17593/img/card/xx-macaron-day.png",
      "SongTitle": "Macaron Day",
      "SongId": "1624",
      "SongArtist": "HyuN",
      "Charts": [
        {
          "Done": "False",
          "Level": "D18",
          "Require": [
            {
              "Done": "False",
              "Description": "At least D13 SS"
            }
          ]
        }
      ]
    },
    {
      "SongBanner": "https://pumpout2.anyhowstep.com:17593/img/card/xx-meteo-science.png",
      "SongTitle": "Meteo5cience (Remix)",
      "SongId": "16D3",
      "SongArtist": "Paul Bazooka",
      "Charts": [
        {
          "Done": "False",
          "Level": "S21",
          "Require": [
            {
              "Done": "False",
              "Description": "Mad5cience S20 PASS (with at least A)"
            },
            {
              "Done": "False",
              "Description": "Meteorize S17 PASS (with at least A)"
            },
            {
              "Done": "False",
              "Description": "Meteo5cience S18 PASS (with at least A)"
            }
          ]
        },
        {
          "Done": "False",
          "Level": "D22",
          "Require": [
            {
              "Done": "False",
              "Description": "Mad5cience D16 PASS (with at least A)"
            },
            {
              "Done": "False",
              "Description": "Meteorize D18 PASS (with at least A)"
            },
            {
              "Done": "False",
              "Description": "Meteo5cience D19 PASS (with at least A)"
            }
          ]
        }
      ]
    },
    {
      "SongBanner": "https://pumpout2.anyhowstep.com:17593/img/card/123.png",
      "SongTitle": "Monolith",
      "SongId": "PE31",
      "SongArtist": "Affinity",
      "Charts": [
        {
          "Done": "False",
          "Level": "S21",
          "Require": [
            {
              "Done": "False",
              "Description": "Clear 40 mission zone quests"
            }
          ]
        }
      ]
    },
    // -- N --
    {
      "SongBanner": "https://pumpout2.anyhowstep.com:17593/img/card/xx-nekkoya.png",
      "SongTitle": "Nekkoya (Pick Me)",
      "SongId": "1649",
      "SongArtist": "Produce 48",
      "Charts": [
        {
          "Done": "False",
          "Level": "S17",
          "Require": [
            {
              "Done": "False",
              "Description": "At least S15 A"
            }
          ]
        }
      ]
    },
    {
      "SongBanner": "https://pumpout2.anyhowstep.com:17593/img/card/xx-nihilism.png",
      "SongTitle": "Nihilism - Another Ver.-",
      "SongId": "1694",
      "SongArtist": "Nato",
      "Charts": [
        {
          "Done": "False",
          "Level": "S21",
          "Require": [
            {
              "Done": "False",
              "Description": "At least A on Love is a Danger Zone pt.2 [Another] S16"
            }
          ]
        },
        {
          "Done": "False",
          "Level": "D19",
          "Require": [
            {
              "Done": "False",
              "Description": "At least A on Love is a Danger Zone pt.2 [Another] S17"
            }
          ]
        },
        {
          "Done": "False",
          "Level": "D23",
          "Require": [
            {
              "Done": "False",
              "Description": "At least S on Love is a Danger Zone pt.2 [Another] S16 and S17"
            }
          ]
        }
      ]
    },
    {
      "SongBanner": "https://pumpout2.anyhowstep.com:17593/img/card/xx-nyarlathotep.png",
      "SongTitle": "Nyarlathotep",
      "SongId": "16F0",
      "SongArtist": "Nato",
      "Charts": [
        {
          "Done": "False",
          "Level": "S18",
          "Require": [
            {
              "Done": "False",
              "Description": "At least S16 A"
            }
          ]
        },
        {
          "Done": "False",
          "Level": "S23",
          "Require": [
            {
              "Done": "False",
              "Description": "Advanced Lv. 8 Title"
            }
          ]
        },
        {
          "Done": "False",
          "Level": "D20",
          "Require": [
            {
              "Done": "False",
              "Description": "Advanced Lv. 1 Title"
            }
          ]
        },
        {
          "Done": "False",
          "Level": "D23",
          "Require": [
            {
              "Done": "False",
              "Description": "Advanced Lv. 9 Title"
            }
          ]
        },
        {
          "Done": "False",
          "Level": "D24",
          "Require": [
            {
              "Done": "False",
              "Description": "Expert Lv. 1 Title"
            }
          ]
        },
        {
          "Done": "False",
          "Level": "D25",
          "Require": [
            {
              "Done": "False",
              "Description": "Expert Lv. 2 Title"
            }
          ]
        }
      ]
    },
    // -- O --
    {
      "SongBanner": "https://pumpout2.anyhowstep.com:17593/img/card/xx-obelisque.png",
      "SongTitle": "Obelisque",
      "SongId": "1680",
      "SongArtist": "ESTi x M2U",
      "Charts": [
        {
          "Done": "False",
          "Level": "S15",
          "Require": [
            {
              "Done": "False",
              "Description": "At least S10 S"
            }
          ]
        },
        {
          "Done": "False",
          "Level": "S17",
          "Require": [
            {
              "Done": "False",
              "Description": "At least S15 S"
            }
          ]
        },
        {
          "Done": "False",
          "Level": "D15",
          "Require": [
            {
              "Done": "False",
              "Description": "At least D11 S"
            }
          ]
        },
        {
          "Done": "False",
          "Level": "D17",
          "Require": [
            {
              "Done": "False",
              "Description": "At least D15 A"
            }
          ]
        }
      ]
    },
    {
      "SongBanner": "https://pumpout2.anyhowstep.com:17593/img/card/xx-obliteration.png",
      "SongTitle": "Obliteration",
      "SongId": "1603",
      "SongArtist": "ATAS",
      "Charts": [
        {
          "Done": "False",
          "Level": "S17",
          "Require": [
            {
              "Done": "False",
              "Description": "At least S14 A"
            }
          ]
        },
        {
          "Done": "False",
          "Level": "D15",
          "Require": [
            {
              "Done": "False",
              "Description": "At least D10 S"
            }
          ]
        },
        {
          "Done": "False",
          "Level": "D19",
          "Require": [
            {
              "Done": "False",
              "Description": "At least D15 S"
            }
          ]
        }
      ]
    },
    {
      "SongBanner": "https://pumpout2.anyhowstep.com:17593/img/card/1631.png",
      "SongTitle": "Orbit Stabilizer",
      "SongId": "1631",
      "SongArtist": "DM Ashura",
      "Charts": [
        {
          "Done": "False",
          "Level": "S19",
          "Require": [
            {
              "Done": "False",
              "Description": "At least S16 S"
            }
          ]
        },
        {
          "Done": "False",
          "Level": "S21",
          "Require": [
            {
              "Done": "False",
              "Description": "At least S19 A"
            }
          ]
        },
        {
          "Done": "False",
          "Level": "D21",
          "Require": [
            {
              "Done": "False",
              "Description": "At least D18 S"
            }
          ]
        },
        {
          "Done": "False",
          "Level": "D23",
          "Require": [
            {
              "Done": "False",
              "Description": "At least D21 A"
            }
          ]
        }
      ]
    },
    // -- P --
    {
      "SongBanner": "https://pumpout2.anyhowstep.com:17593/img/card/16A1.png",
      "SongTitle": "Papasito feat. KuTiNa",
      "SongId": "16A1",
      "SongArtist": "Yakikaze & Cashew",
      "Charts": [
        {
          "Done": "False",
          "Level": "S20",
          "Require": [
            {
              "Done": "False",
              "Description": "At least S15 S"
            },
            {
              "Done": "False",
              "Description": "At least A on S16"
            }
          ]
        },
        {
          "Done": "False",
          "Level": "D21",
          "Require": [
            {
              "Done": "False",
              "Description": "At least D16 S"
            },
            {
              "Done": "False",
              "Description": "At least A on D18"
            }
          ]
        }
      ]
    },
    {
      "SongBanner": "https://pumpout2.anyhowstep.com:17593/img/card/xx-poseidon.png",
      "SongTitle": "Poseidon",
      "SongId": "1626",
      "SongArtist": "Quree",
      "Charts": [
        {
          "Done": "False",
          "Level": "S14",
          "Require": [
            {
              "Done": "False",
              "Description": "At least S10 S"
            }
          ]
        },
        {
          "Done": "False",
          "Level": "D22",
          "Require": [
            {
              "Done": "False",
              "Description": "At least D16 SS"
            }
          ]
        }
      ]
    },
    {
      "SongBanner": "https://pumpout2.anyhowstep.com:17593/img/card/16D4.png",
      "SongTitle": "Prime Time (Remix)",
      "SongId": "16D4",
      "SongArtist": "Cashew",
      "Charts": [
        {
          "Done": "False",
          "Level": "S21",
          "Require": [
            {
              "Done": "False",
              "Description": "At least S15 SS"
            }
          ]
        },
        {
          "Done": "False",
          "Level": "S23",
          "Require": [
            {
              "Done": "False",
              "Description": "At least S21 A"
            }
          ]
        },
        {
          "Done": "False",
          "Level": "D26",
          "Require": [
            {
              "Done": "False",
              "Description": "Get >14 million points on DP24? (Unlocked with 15.3 million points)"
            }
          ]
        }
      ]
    },
    // -- Q --
    // -- R --
    {
      "SongBanner": "https://pumpout2.anyhowstep.com:17593/img/card/xx-rage-of-fire.png",
      "SongTitle": "Rage of Fire",
      "SongId": "1681",
      "SongArtist": "MAX",
      "Charts": [
        {
          "Done": "False",
          "Level": "S18",
          "Require": [
            {
              "Done": "False",
              "Description": "At least S16 A"
            }
          ]
        },
        {
          "Done": "False",
          "Level": "D19",
          "Require": [
            {
              "Done": "False",
              "Description": "At least D17 A"
            }
          ]
        }
      ]
    },
    {
      "SongBanner": "https://pumpout2.anyhowstep.com:17593/img/card/1686.png",
      "SongTitle": "Rising Star",
      "SongId": "1686",
      "SongArtist": "M2U",
      "Charts": [
        {
          "Done": "False",
          "Level": "S17",
          "Require": [
            {
              "Done": "False",
              "Description": "At least S15 A"
            }
          ]
        },
        {
          "Done": "False",
          "Level": "D19",
          "Require": [
            {
              "Done": "False",
              "Description": "At least D17 A"
            }
          ]
        }
      ]
    },
    // -- S --
    {
      "SongBanner": "https://pumpout2.anyhowstep.com:17593/img/card/xx-skeptic.png",
      "SongTitle": "Skeptic",
      "SongId": "1618",
      "SongArtist": "Doin",
      "Charts": [
        {
          "Done": "False",
          "Level": "S12",
          "Require": [
            {
              "Done": "False",
              "Description": "AM.Pass level 50"
            }
          ]
        },
        {
          "Done": "False",
          "Level": "S18",
          "Require": [
            {
              "Done": "False",
              "Description": "AM.Pass level 55"
            }
          ]
        },
        {
          "Done": "False",
          "Level": "S22",
          "Require": [
            {
              "Done": "False",
              "Description": "AM.Pass level 60"
            }
          ]
        },
        {
          "Done": "False",
          "Level": "S24",
          "Require": [
            {
              "Done": "False",
              "Description": "AM.Pass level 65"
            }
          ]
        },
        {
          "Done": "False",
          "Level": "D14",
          "Require": [
            {
              "Done": "False",
              "Description": "AM.Pass level 70"
            }
          ]
        },
        {
          "Done": "False",
          "Level": "D22",
          "Require": [
            {
              "Done": "False",
              "Description": "AM.Pass level 75"
            }
          ]
        },
        {
          "Done": "False",
          "Level": "D25",
          "Require": [
            {
              "Done": "False",
              "Description": "AM.Pass level 80"
            }
          ]
        }
      ]
    },
    {
      "SongBanner": "https://pumpout2.anyhowstep.com:17593/img/card/1658.png",
      "SongTitle": "Starry Night",
      "SongId": "1658",
      "SongArtist": "Mamamoo",
      "Charts": [
        {
          "Done": "False",
          "Level": "S16",
          "Require": [
            {
              "Done": "False",
              "Description": "S01 SSS"
            }
          ]
        },
        {
          "Done": "False",
          "Level": "D17",
          "Require": [
            {
              "Done": "False",
              "Description": "S01 SSS"
            }
          ]
        }
      ]
    },
    {
      "SongBanner": "https://pumpout2.anyhowstep.com:17593/img/card/190.png",
      "SongTitle": "Super Fantasy",
      "SongId": "1419",
      "SongArtist": "SHK",
      "Charts": [
        {
          "Done": "False",
          "Level": "S20",
          "Require": [
            {
              "Done": "False",
              "Description": "Clear 24 mission zone quests"
            }
          ]
        }
      ]
    },
    // -- T --
    {
      "SongBanner": "https://pumpout2.anyhowstep.com:17593/img/card/1629.png",
      "SongTitle": "Tales of Pumpnia",
      "SongId": "1629",
      "SongArtist": "Applesoda",
      "Charts": [
        {
          "Done": "False",
          "Level": "S19",
          "Require": [
            {
              "Done": "False",
              "Description": "At least S16 S"
            }
          ]
        },
        {
          "Done": "False",
          "Level": "D20",
          "Require": [
            {
              "Done": "False",
              "Description": "At least D17 S"
            }
          ]
        }
      ]
    },
    {
      "SongBanner": "https://pumpout2.anyhowstep.com:17593/img/card/1635.png",
      "SongTitle": "Tantanmen",
      "SongId": "1635",
      "SongArtist": "Memme",
      "Charts": [
        {
          "Done": "False",
          "Level": "S20",
          "Require": [
            {
              "Done": "False",
              "Description": "At least S17 S"
            }
          ]
        },
        {
          "Done": "False",
          "Level": "D23",
          "Require": [
            {
              "Done": "False",
              "Description": "At least D20 S"
            }
          ]
        }
      ]
    },
    {
      "SongBanner": "https://pumpout2.anyhowstep.com:17593/img/card/xx-the-little-prince.png",
      "SongTitle": "The Little Prince (Prod. Godic)",
      "SongId": "1642",
      "SongArtist": "HAON, PULLIK",
      "Charts": [
        {
          "Done": "False",
          "Level": "S18",
          "Require": [
            {
              "Done": "False",
              "Description": "At least A on Boong Boong S18"
            }
          ]
        },
        {
          "Done": "False",
          "Level": "D16",
          "Require": [
            {
              "Done": "False",
              "Description": "At least A on Boong Boong D16"
            }
          ]
        }
      ]
    },
    {
      "SongBanner": "https://pumpout2.anyhowstep.com:17593/img/card/xx-time-for-the-moon-night.png",
      "SongTitle": "Time For The Moon Night",
      "SongId": "1660",
      "SongArtist": "GFriend",
      "Charts": [
        {
          "Done": "False",
          "Level": "S18",
          "Require": [
            {
              "Done": "False",
              "Description": "At least S16 A"
            }
          ]
        },
        {
          "Done": "False",
          "Level": "D21",
          "Require": [
            {
              "Done": "False",
              "Description": "At least D18 A"
            }
          ]
        }
      ]
    },
    {
      "SongBanner": "https://pumpout2.anyhowstep.com:17593/img/card/xx-timing.png",
      "SongTitle": "Timing",
      "SongId": "1644",
      "SongArtist": "Highteen",
      "Charts": [
        {
          "Done": "False",
          "Level": "S17",
          "Require": [
            {
              "Done": "False",
              "Description": "At least S15 A"
            }
          ]
        },
        {
          "Done": "False",
          "Level": "D18",
          "Require": [
            {
              "Done": "False",
              "Description": "At least D16 A"
            }
          ]
        }
      ]
    },
    // -- U --
    // -- V --
    {
      "SongBanner": "https://pumpout2.anyhowstep.com:17593/img/card/xx-vanish.png",
      "SongTitle": "Vanish",
      "SongId": "1628",
      "SongArtist": "Applesoda",
      "Charts": [
        {
          "Done": "False",
          "Level": "S17",
          "Require": [
            {
              "Done": "False",
              "Description": "At least S12 S"
            }
          ]
        },
        {
          "Done": "False",
          "Level": "D18",
          "Require": [
            {
              "Done": "False",
              "Description": "At least D12 SS"
            }
          ]
        },
        {
          "Done": "False",
          "Level": "D22",
          "Require": [
            {
              "Done": "False",
              "Description": "Advanced Lv. 6 Title"
            }
          ]
        }
      ]
    },
    {
      "SongBanner": "https://pumpout2.anyhowstep.com:17593/img/card/xx-very-nice.png",
      "SongTitle": "Very Nice",
      "SongId": "1662",
      "SongArtist": "Seventeen",
      "Charts": [
        {
          "Done": "False",
          "Level": "S14",
          "Require": [
            {
              "Done": "False",
              "Description": "AM.Pass Login"
            }
          ]
        },
        {
          "Done": "False",
          "Level": "S17",
          "Require": [
            {
              "Done": "False",
              "Description": "At least S14 A"
            }
          ]
        },
        {
          "Done": "False",
          "Level": "D15",
          "Require": [
            {
              "Done": "False",
              "Description": "At least S14 A"
            }
          ]
        },
        {
          "Done": "False",
          "Level": "D18",
          "Require": [
            {
              "Done": "False",
              "Description": "At least D15 S"
            }
          ]
        }
      ]
    },
    // -- W --
    {
      "SongBanner": "https://pumpout2.anyhowstep.com:17593/img/card/xx-wedding-crashers.png",
      "SongTitle": "Wedding Crashers",
      "SongId": "1601",
      "SongArtist": "SHK",
      "Charts": [
        {
          "Done": "False",
          "Level": "S18",
          "Require": [
            {
              "Done": "False",
              "Description": "AM.Pass Login"
            }
          ]
        },
        {
          "Done": "False",
          "Level": "S21",
          "Require": [
            {
              "Done": "False",
              "Description": "At least S18 A"
            }
          ]
        },
        {
          "Done": "False",
          "Level": "D19",
          "Require": [
            {
              "Done": "False",
              "Description": "At least D13 SS"
            }
          ]
        },
        {
          "Done": "False",
          "Level": "D22",
          "Require": [
            {
              "Done": "False",
              "Description": "Advanced Lv. 5 Title"
            }
          ]
        },
        {
          "Done": "False",
          "Level": "CO-OP X 3",
          "Require": [
            {
              "Done": "False",
              "Description": "Play (and pass) co-op charts 30 times"
            }
          ]
        }
      ]
    },
    // -- X --
    {
      "SongBanner": "https://pumpout2.anyhowstep.com:17593/img/card/xx-xeroize.png",
      "SongTitle": "Xeroize",
      "SongId": "1685",
      "SongArtist": "FE",
      "Charts": [
        {
          "Done": "False",
          "Level": "S21",
          "Require": [
            {
              "Done": "False",
              "Description": "Random / Play it with someone who has this"
            }
          ]
        },
        {
          "Done": "False",
          "Level": "S24",
          "Require": [
            {
              "Done": "False",
              "Description": "Random / Play it with someone who has this"
            }
          ]
        },
        {
          "Done": "False",
          "Level": "D22",
          "Require": [
            {
              "Done": "False",
              "Description": "Advanced Lv. 7 Title"
            }
          ]
        },
        {
          "Done": "False",
          "Level": "D25",
          "Require": [
            {
              "Done": "False",
              "Description": "Random / Play it with someone who has this"
            }
          ]
        }
      ]
    },
    // -- Y --
    {
      "SongBanner": "https://pumpout2.anyhowstep.com:17593/img/card/xx-you-and-i.png",
      "SongTitle": "You And I",
      "SongId": "1664",
      "SongArtist": "Dreamcatcher",
      "Charts": [
        {
          "Done": "False",
          "Level": "S21",
          "Require": [
            {
              "Done": "False",
              "Description": "Chase me S20 PASS (with at least A)"
            },
            {
              "Done": "False",
              "Description": "Good Night S20 PASS (with at least A)"
            },
            {
              "Done": "False",
              "Description": "Fly High S18 PASS (with at least A)"
            }
          ]
        },
        {
          "Done": "False",
          "Level": "D20",
          "Require": [
            {
              "Done": "False",
              "Description": "Chase me D18 PASS (with at least A)"
            },
            {
              "Done": "False",
              "Description": "Good Night D19 PASS (with at least A)"
            },
            {
              "Done": "False",
              "Description": "Fly High D19 PASS (with at least A)"
            }
          ]
        },
        {
          "Done": "False",
          "Level": "D25",
          "Require": [
            {
              "Done": "False",
              "Description": "Chase me D23 PASS (with at least A)"
            },
            {
              "Done": "False",
              "Description": "Good Night D24 PASS (with at least A)"
            }
          ]
        }
      ]
    }
    // -- Z --
  ]
}